orkestr_core/__init__.py
orkestr_core/base/__init__.py
orkestr_core/base/cluster.py
orkestr_core/base/datastore.py
orkestr_core/base/drift_detector/README.md
orkestr_core/base/drift_detector/__init__.py
orkestr_core/base/drift_detector/drift_detector.py
orkestr_core/base/events/__init__.py
orkestr_core/base/events/event_bus.py
orkestr_core/base/events/event_library/__init__.py
orkestr_core/base/events/event_library/cluster_events.py
orkestr_core/base/events/event_library/event.py
orkestr_core/base/events/event_library/node_events.py
orkestr_core/base/events/handlers/__init__.py
orkestr_core/base/events/handlers/cluster_event_handlers.py
orkestr_core/base/events/handlers/node_event_handlers.py
orkestr_core/base/node.py
orkestr_core/base/node_spec.py
orkestr_core/base/orchestrator/__init__.py
orkestr_core/base/orchestrator/cluster_orchestrator.py
orkestr_core/base/orchestrator/node_orchestrator.py
orkestr_core/base/orkestr.py
orkestr_core/base/provider.py
orkestr_core/base/provider_client.py
orkestr_core/base/scheduler/__init__.py
orkestr_core/base/scheduler/async_scheduler.py
orkestr_core/base/scheduler/scheduler.py
orkestr_core/base/scheduler/scheduler_action.py
orkestr_core/base/service.py
orkestr_core/constants/providers.py
orkestr_core/datastores/dynamodb/README.md
orkestr_core/datastores/dynamodb/dynamodb_datastore.py
orkestr_core/datastores/global_datastore.py
orkestr_core/datastores/sqlite/README.md
orkestr_core/datastores/sqlite/sqlite_datastore.py
orkestr_core/providers/lambda_labs/README.md
orkestr_core/providers/lambda_labs/__init__.py
orkestr_core/providers/lambda_labs/base/lambda_node.py
orkestr_core/providers/lambda_labs/lambda_labs_client.py
orkestr_core/providers/lambda_labs/provider.py
orkestr_core/providers/provider_registry.py
orkestr_core/providers/test_provider/README.md
orkestr_core/providers/test_provider/__init__.py
orkestr_core/providers/test_provider/base/test_node.py
orkestr_core/providers/test_provider/provider.py
orkestr_core-0.1.9.dist-info/LICENSE
orkestr_core-0.1.9.dist-info/METADATA
orkestr_core-0.1.9.dist-info/WHEEL
orkestr_core-0.1.9.dist-info/RECORD
