Metadata-Version: 2.3
Name: orkestr-core
Version: 0.1.9
Summary: Framework for orchestrating infrastructure and services in a multi-cloud environment
License: MIT
Author: joel.gee.roy
Author-email: joel.gee.roy@murf.ai
Requires-Python: >=3.11
Classifier: License :: OSI Approved :: MIT License
Classifier: Programming Language :: Python :: 3
Classifier: Programming Language :: Python :: 3.11
Classifier: Programming Language :: Python :: 3.12
Classifier: Programming Language :: Python :: 3.13
Requires-Dist: httpx (>=0.28.1,<0.29.0)
Requires-Dist: pydantic (>=2.10.6,<3.0.0)
Requires-Dist: python-dotenv (>=1.1.0,<2.0.0)
